pytabs/__init__.py
pytabs/analyse.py
pytabs/analysis_results.py
pytabs/analysis_results_setup.py
pytabs/area_elm.py
pytabs/area_obj.py
pytabs/combo.py
pytabs/constraint.py
pytabs/database_tables.py
pytabs/diaphragm.py
pytabs/enumerations.py
pytabs/error_handle.py
pytabs/etabs_config.py
pytabs/frame_obj.py
pytabs/grid_sys.py
pytabs/group.py
pytabs/line_elm.py
pytabs/link_obj.py
pytabs/load_cases.py
pytabs/load_patterns.py
pytabs/model.py
pytabs/pier_label.py
pytabs/point_elm.py
pytabs/point_obj.py
pytabs/property.py
pytabs/pytabs_config.ini
pytabs/pytabs_config.py
pytabs/select.py
pytabs/spandrel_label.py
pytabs/story.py
pytabs/tendon_obj.py
pytabs/tower.py
pytabs/view.py
pytabs/cases/__init__.py
pytabs/cases/case_direct_history_linear.py
pytabs/cases/case_direct_history_nonlinear.py
pytabs/cases/case_hyperstatic.py
pytabs/cases/case_modal_eigen.py
pytabs/cases/case_modal_history_linear.py
pytabs/cases/case_modal_history_nonlinear.py
pytabs/cases/case_modal_ritz.py
pytabs/cases/case_response_spectrum.py
pytabs/cases/case_static_linear.py
pytabs/cases/case_static_nonlinear.py
pytabs/cases/case_static_nonlinear_staged.py
pytabs/properties/__init__.py
pytabs/properties/prop_area.py
pytabs/properties/prop_area_spring.py
pytabs/properties/prop_frame.py
pytabs/properties/prop_line_spring.py
pytabs/properties/prop_link.py
pytabs/properties/prop_material.py
pytabs/properties/prop_point_spring.py
pytabs/properties/prop_rebar.py
pytabs/properties/prop_tendon.py
pytabs-0.2.1.dist-info/METADATA
pytabs-0.2.1.dist-info/WHEEL
pytabs-0.2.1.dist-info/licenses/LICENSE
pytabs-0.2.1.dist-info/RECORD
