Metadata-Version: 2.1
Name: pytabs
Version: 0.2.1
Summary: A python wrapper for the CSi ETABS .NET API
Project-URL: Homepage, https://github.com/mitchell-tesch/pytabs
Project-URL: Issues, https://github.com/mitchell-tesch/pytabs/issues
Project-URL: Repository, https://github.com/mitchell-tesch/pytabs
Author: Mitchell Tesch
Author-email: mitchell.z.tesch@gmail.com
License-File: LICENSE
Classifier: Development Status :: 4 - Beta
Classifier: Intended Audience :: Developers
Classifier: License :: OSI Approved :: MIT License
Classifier: Natural Language :: English
Classifier: Operating System :: Microsoft :: Windows
Classifier: Programming Language :: Python :: 3.10
Classifier: Programming Language :: Python :: 3.11
Classifier: Programming Language :: Python :: 3.12
Classifier: Topic :: Scientific/Engineering
Requires-Python: >=3.10
Requires-Dist: pythonnet
Provides-Extra: examples
Requires-Dist: pandas; extra == 'examples'
Requires-Dist: xlwings; extra == 'examples'
